assuan/.client.py.swp
assuan/.common.py.swp
assuan/.server.py.swp
assuan/__init__.py
assuan/client.py
assuan/common.py
assuan/exception.py
assuan/py.typed
assuan/server.py
assuan-0.2.1b1.dist-info/LICENSE
assuan-0.2.1b1.dist-info/WHEEL
assuan-0.2.1b1.dist-info/METADATA
assuan-0.2.1b1.dist-info/RECORD
